[
  {
    "Bank Name": "Bank of Afghanistan",
    "query": "site:dab.gov.af \"Research & Publications\"",
    "error": {
      "data": [
        {
          "error": {
            "type": "HANDLINE",
            "code": "PROCESSING",
            "message": null,
            "query": {
              "q": "site:dab.gov.af \"Research & Publications\""
            }
          }
        }
      ],
      "meta": {
        "took": 0.5637130737304688
      }
    }
  },
  {
    "Bank Name": "Bank of Afghanistan",
    "query": "site:dab.gov.af \"press releases\"",
    "error": {
      "data": [
        {
          "error": {
            "type": "HANDLINE",
            "code": "PROCESSING",
            "message": null,
            "query": {
              "q": "site:dab.gov.af \"press releases\""
            }
          }
        }
      ],
      "meta": {
        "took": 0.4132235050201416
      }
    }
  },
  {
    "Bank Name": "Bank of Albania",
    "query": "site:bankofalbania.org \"news archive\"",
    "error": {
      "data": [
        {
          "error": {
            "type": "HANDLINE",
            "code": "PROCESSING",
            "message": null,
            "query": {
              "q": "site:bankofalbania.org \"news archive\""
            }
          }
        }
      ],
      "meta": {
        "took": 0.6509978771209717
      }
    }
  },
  {
    "Bank Name": "Bank of Albania",
    "query": "site:bankofalbania.org \"publication archive\"",
    "error": {
      "data": [
        {
          "error": {
            "type": "HANDLINE",
            "code": "PROCESSING",
            "message": null,
            "query": {
              "q": "site:bankofalbania.org \"publication archive\""
            }
          }
        }
      ],
      "meta": {
        "took": 0.9642541408538818
      }
    }
  },
  {
    "Bank Name": "Bank of Algeria",
    "query": "site:bank-of-algeria.dz \"press releases\"",
    "error": {
      "data": [
        {
          "error": {
            "type": "HANDLINE",
            "code": "PROCESSING",
            "message": null,
            "query": {
              "q": "site:bank-of-algeria.dz \"press releases\""
            }
          }
        }
      ],
      "meta": {
        "took": 0.30219459533691406
      }
    }
  },
  {
    "Bank Name": "Bank of Algeria",
    "query": "site:bank-of-algeria.dz \"statistical data\"",
    "error": {
      "data": [
        {
          "error": {
            "type": "HANDLINE",
            "code": "PROCESSING",
            "message": null,
            "query": {
              "q": "site:bank-of-algeria.dz \"statistical data\""
            }
          }
        }
      ],
      "meta": {
        "took": 0.9821531772613525
      }
    }
  },
  {
    "Bank Name": "Bank of Algeria",
    "query": "site:bank-of-algeria.dz library",
    "error": {
      "data": [
        {
          "error": {
            "type": "HANDLINE",
            "code": "PROCESSING",
            "message": null,
            "query": {
              "q": "site:bank-of-algeria.dz library"
            }
          }
        }
      ],
      "meta": {
        "took": 0.9454033374786377
      }
    }
  },
  {
    "Bank Name": "National Bank of Angola",
    "query": "site:bna.ao arquivo",
    "error": {
      "data": [
        {
          "error": {
            "type": "HANDLINE",
            "code": "PROCESSING",
            "message": null,
            "query": {
              "q": "site:bna.ao arquivo"
            }
          }
        }
      ],
      "meta": {
        "took": 0.3672761917114258
      }
    }
  },
  {
    "Bank Name": "National Bank of Angola",
    "query": "site:bna.ao biblioteca",
    "error": {
      "data": [
        {
          "error": {
            "type": "HANDLINE",
            "code": "PROCESSING",
            "message": null,
            "query": {
              "q": "site:bna.ao biblioteca"
            }
          }
        }
      ],
      "meta": {
        "took": 0.6244547367095947
      }
    }
  },
  {
    "Bank Name": "National Bank of Angola",
    "query": "site:bna.ao repositório",
    "error": {
      "data": [
        {
          "error": {
            "type": "HANDLINE",
            "code": "PROCESSING",
            "message": null,
            "query": {
              "q": "site:bna.ao repositório"
            }
          }
        }
      ],
      "meta": {
        "took": 0.25789380073547363
      }
    }
  },
  {
    "Bank Name": "National Bank of Angola",
    "query": "site:bna.ao \"publicações periódicas\"",
    "error": {
      "data": [
        {
          "error": {
            "type": "HANDLINE",
            "code": "PROCESSING",
            "message": null,
            "query": {
              "q": "site:bna.ao \"publicações periódicas\""
            }
          }
        }
      ],
      "meta": {
        "took": 0.7584109306335449
      }
    }
  },
  {
    "Bank Name": "Central Bank of Armenia",
    "query": "site:cba.am \"news archive\"",
    "error": {
      "data": [
        {
          "error": {
            "type": "HANDLINE",
            "code": "PROCESSING",
            "message": null,
            "query": {
              "q": "site:cba.am \"news archive\""
            }
          }
        }
      ],
      "meta": {
        "took": 0.3434178829193115
      }
    }
  },
  {
    "Bank Name": "Reserve Bank of Australia",
    "query": "site:rba.gov.au \"monetary policy documents\"",
    "error": {
      "data": [
        {
          "error": {
            "type": "HANDLINE",
            "code": "PROCESSING",
            "message": null,
            "query": {
              "q": "site:rba.gov.au \"monetary policy documents\""
            }
          }
        }
      ],
      "meta": {
        "took": 0.33046770095825195
      }
    }
  },
  {
    "Bank Name": "Bank of Afghanistan",
    "query": "site:dab.gov.af \"Research & Publications\"",
    "error": {
      "data": [
        {
          "error": {
            "type": "HANDLINE",
            "code": "PROCESSING",
            "message": null,
            "query": {
              "q": "site:dab.gov.af \"Research & Publications\""
            }
          }
        }
      ],
      "meta": {
        "took": 1.0510430335998535
      }
    }
  },
  {
    "Bank Name": "Bank of Albania",
    "query": "site:bankofalbania.org \"news archive\"",
    "error": {
      "data": [
        {
          "error": {
            "type": "HANDLINE",
            "code": "PROCESSING",
            "message": null,
            "query": {
              "q": "site:bankofalbania.org \"news archive\""
            }
          }
        }
      ],
      "meta": {
        "took": 0.3434255123138428
      }
    }
  },
  {
    "Bank Name": "Bank of Algeria",
    "query": "site:bank-of-algeria.dz \"press releases\"",
    "error": {
      "data": [
        {
          "error": {
            "type": "HANDLINE",
            "code": "PROCESSING",
            "message": null,
            "query": {
              "q": "site:bank-of-algeria.dz \"press releases\""
            }
          }
        }
      ],
      "meta": {
        "took": 0.6230130195617676
      }
    }
  },
  {
    "Bank Name": "Bank of Algeria",
    "query": "site:bank-of-algeria.dz \"statistical data\"",
    "error": {
      "data": [
        {
          "error": {
            "type": "HANDLINE",
            "code": "PROCESSING",
            "message": null,
            "query": {
              "q": "site:bank-of-algeria.dz \"statistical data\""
            }
          }
        }
      ],
      "meta": {
        "took": 0.3852109909057617
      }
    }
  },
  {
    "Bank Name": "Bank of Algeria",
    "query": "site:bank-of-algeria.dz library",
    "error": {
      "data": [
        {
          "error": {
            "type": "HANDLINE",
            "code": "PROCESSING",
            "message": null,
            "query": {
              "q": "site:bank-of-algeria.dz library"
            }
          }
        }
      ],
      "meta": {
        "took": 0.5870859622955322
      }
    }
  },
  {
    "Bank Name": "National Bank of Angola",
    "query": "site:bna.ao \"comunicados de imprensa\"",
    "error": {
      "data": [
        {
          "error": {
            "type": "HANDLINE",
            "code": "PROCESSING",
            "message": null,
            "query": {
              "q": "site:bna.ao \"comunicados de imprensa\""
            }
          }
        }
      ],
      "meta": {
        "took": 0.33191895484924316
      }
    }
  },
  {
    "Bank Name": "National Bank of Angola",
    "query": "site:bna.ao \"dados estatísticos\"",
    "error": {
      "data": [
        {
          "error": {
            "type": "HANDLINE",
            "code": "PROCESSING",
            "message": null,
            "query": {
              "q": "site:bna.ao \"dados estatísticos\""
            }
          }
        }
      ],
      "meta": {
        "took": 0.8840832710266113
      }
    }
  },
  {
    "Bank Name": "National Bank of Angola",
    "query": "site:bna.ao arquivo",
    "error": {
      "data": [
        {
          "error": {
            "type": "HANDLINE",
            "code": "PROCESSING",
            "message": null,
            "query": {
              "q": "site:bna.ao arquivo"
            }
          }
        }
      ],
      "meta": {
        "took": 0.6085638999938965
      }
    }
  },
  {
    "Bank Name": "National Bank of Angola",
    "query": "site:bna.ao biblioteca",
    "error": {
      "data": [
        {
          "error": {
            "type": "HANDLINE",
            "code": "PROCESSING",
            "message": null,
            "query": {
              "q": "site:bna.ao biblioteca"
            }
          }
        }
      ],
      "meta": {
        "took": 0.9398586750030518
      }
    }
  },
  {
    "Bank Name": "National Bank of Angola",
    "query": "site:bna.ao repositório",
    "error": {
      "data": [
        {
          "error": {
            "type": "HANDLINE",
            "code": "PROCESSING",
            "message": null,
            "query": {
              "q": "site:bna.ao repositório"
            }
          }
        }
      ],
      "meta": {
        "took": 0.30463242530822754
      }
    }
  },
  {
    "Bank Name": "National Bank of Angola",
    "query": "site:bna.ao \"relatórios anuais\"",
    "error": {
      "data": [
        {
          "error": {
            "type": "HANDLINE",
            "code": "PROCESSING",
            "message": null,
            "query": {
              "q": "site:bna.ao \"relatórios anuais\""
            }
          }
        }
      ],
      "meta": {
        "took": 0.829390287399292
      }
    }
  },
  {
    "Bank Name": "National Bank of Angola",
    "query": "site:bna.ao \"publicações periódicas\"",
    "error": {
      "data": [
        {
          "error": {
            "type": "HANDLINE",
            "code": "PROCESSING",
            "message": null,
            "query": {
              "q": "site:bna.ao \"publicações periódicas\""
            }
          }
        }
      ],
      "meta": {
        "took": 0.4037315845489502
      }
    }
  },
  {
    "Bank Name": "Central Bank of Armenia",
    "query": "site:cba.am \"economic reviews\"",
    "error": {
      "data": [
        {
          "error": {
            "type": "HANDLINE",
            "code": "PROCESSING",
            "message": null,
            "query": {
              "q": "site:cba.am \"economic reviews\""
            }
          }
        }
      ],
      "meta": {
        "took": 0.3352169990539551
      }
    }
  },
  {
    "Bank Name": "Central Bank of Armenia",
    "query": "site:cba.am \"news archive\"",
    "error": {
      "data": [
        {
          "error": {
            "type": "HANDLINE",
            "code": "PROCESSING",
            "message": null,
            "query": {
              "q": "site:cba.am \"news archive\""
            }
          }
        }
      ],
      "meta": {
        "took": 0.4484844207763672
      }
    }
  }
]